openair/__init__.py
openair/__init__.pyi
openair/openair.cpython-39-x86_64-linux-gnu.so
openair/py.typed
openair_rs_py-0.1.4.dist-info/METADATA
openair_rs_py-0.1.4.dist-info/WHEEL
openair_rs_py-0.1.4.dist-info/licenses/LICENSE-APACHE
openair_rs_py-0.1.4.dist-info/licenses/LICENSE-MIT
openair_rs_py-0.1.4.dist-info/RECORD
