Metadata-Version: 2.4
Name: openair-rs-py
Version: 0.1.4
Classifier: Development Status :: 4 - Beta
Classifier: Intended Audience :: Developers
Classifier: License :: OSI Approved :: MIT License
Classifier: License :: OSI Approved :: Apache Software License
Classifier: Programming Language :: Python :: 3
Classifier: Programming Language :: Python :: 3.8
Classifier: Programming Language :: Python :: 3.9
Classifier: Programming Language :: Python :: 3.10
Classifier: Programming Language :: Python :: 3.11
Classifier: Programming Language :: Python :: 3.12
Classifier: Programming Language :: Python :: 3.13
Classifier: Programming Language :: Rust
Requires-Dist: black>=25.1.0 ; extra == 'dev'
Requires-Dist: flake8>=7.3.0 ; extra == 'dev'
Requires-Dist: isort>=6.0.1 ; extra == 'dev'
Requires-Dist: maturin>=1.9.1 ; extra == 'dev'
Requires-Dist: mypy>=1.16.1 ; extra == 'dev'
Requires-Dist: pre-commit>=4.2.0 ; extra == 'dev'
Requires-Dist: pydocstyle>=6.3.0 ; extra == 'dev'
Requires-Dist: twine>=6.1.0 ; extra == 'dev'
Provides-Extra: dev
License-File: LICENSE-APACHE
License-File: LICENSE-MIT
Summary: Python bindings for OpenAir airspace file parser
Keywords: airspace,aviation,openair,parser
Home-Page: https://github.com/dbrgn/openair-rs/
Author: Danilo Bargen <mail@dbrgn.ch>
Author-email: Danilo Bargen <mail@dbrgn.ch>, Simon Steiner <simonsteiner@users.noreply.github.com>
License: MIT/Apache-2.0
Requires-Python: >=3.8
Project-URL: Source Code, https://github.com/dbrgn/openair-rs/
